[
  {
    "id": 1,
    "date": "20020526",
    "subject": 2,
    "subject_name": "인간공학",
    "question_no": 32,
    "question": "잔상(after images)에 관한 설명 중 올바른 것은? ❶ 양잔상이란 흑은 흑으로 시신경의 흥분이 남아 있는 상 태를 일컫는다.",
    "choices": {
      "2": "60 ㏈",
      "3": "80 ㏈ ❹ 120㏈",
      "4": "자극의 보색이 잔상으로 남는 것은 양잔상에 해당된다. 33. 듣기가 불쾌해지는(통각의 역) 소리의 강도는 몇 데시벨(㏈) 부터인가?",
      "1": "40 ㏈"
    },
    "answers": [
      1
    ],
    "explanation": ""
  },
  {
    "id": 2,
    "date": "20020526",
    "subject": 2,
    "subject_name": "인간공학",
    "question_no": 39,
    "question": "입사광속(入射光線)의 단위면적당 밀도를 그 면의 무엇이라 고 하는가?",
    "choices": {
      "1": "타이핑(typing) - 쓰고, 읽기 - 정밀작업 ❷ 정밀작업 - 쓰고, 읽기 - 타이핑",
      "2": "광도 ❸ 조도",
      "4": "정밀작업 - 타이핑 - 쓰고, 읽기",
      "3": "쓰고, 읽기 - 정밀작업 - 타이핑"
    },
    "answers": [
      3
    ],
    "explanation": ""
  },
  {
    "id": 3,
    "date": "20020526",
    "subject": 3,
    "subject_name": "공업재료 및 모형제작론",
    "question_no": 45,
    "question": "점토의 소성시 변형을 가장 많이 일으키는 것은?",
    "choices": {
      "2": "석영 성분이 많은 것",
      "3": "투시도",
      "4": "드로잉",
      "1": "스케치 ❷ 렌더링"
    },
    "answers": [
      1
    ],
    "explanation": ""
  },
  {
    "id": 4,
    "date": "20020526",
    "subject": 3,
    "subject_name": "공업재료 및 모형제작론",
    "question_no": 50,
    "question": "도면에 치수기입시 제일 집중적으로 기입하는 투상도는?",
    "choices": {
      "1": "평면도 ❷ 정면도",
      "3": "1 : 10 : 15",
      "4": "2 : 10 : 15",
      "2": "1 : 15 : 20"
    },
    "answers": [
      2
    ],
    "explanation": ""
  },
  {
    "id": 5,
    "date": "20020526",
    "subject": 4,
    "subject_name": "색채학",
    "question_no": 68,
    "question": "다음 색 중 보색관계에 있지 않은 색은? (단, 20색상환에서)",
    "choices": {
      "1": "색상대비",
      "2": "적색보다 명도, 채도 모두 높아졌다.",
      "4": "적색보다 명도, 채도 모두 낮아졌다.",
      "3": "적색보다 명도는 낮아졌고 채도는 높아졌다."
    },
    "answers": [
      3
    ],
    "explanation": ""
  },
  {
    "id": 6,
    "date": "20020526",
    "subject": 4,
    "subject_name": "색채학",
    "question_no": 77,
    "question": "감법 혼색의 3원색이 아닌 것은?",
    "choices": {
      "1": "회색",
      "2": "자주",
      "3": "노랑 ❹ 주황",
      "4": "회색계통이나 난색계 79. 한국산업규격의 안전 색채 사용 통칙에서 \"위험\"을 표시하는 기본색은?"
    },
    "answers": [
      4
    ],
    "explanation": ""
  },
  {
    "id": 7,
    "date": "20020908",
    "subject": 1,
    "subject_name": "제품디자인론",
    "question_no": 2,
    "question": "디자인사에 있어서 기능주의 표현과 가장 관계가 적은 사람 은?",
    "choices": {
      "1": "호라티오 그리노프(Horatio Greenough)",
      "2": "ADI",
      "3": "CCI",
      "4": "JIDA"
    },
    "answers": [
      4
    ],
    "explanation": ""
  },
  {
    "id": 8,
    "date": "20020908",
    "subject": 1,
    "subject_name": "제품디자인론",
    "question_no": 11,
    "question": "다음 중 제품 디자인의 영역과 거리가 먼 것은?",
    "choices": {
      "2": "1900년 파리 엑스포 - 아르누보",
      "3": "1925년 파리 엑스포 - 아르데코 ❹ 1930년 스톡홀름 엑스포 - 신조형주의",
      "4": "완구디자인 12. 세계 산업 대박람회는 디자인 운동의 중요한 계기가 되었 다. 다음 중 연결이 바르지 못한 것은?",
      "1": "1851년 런던 산업 대박람회 - 미술공예운동"
    },
    "answers": [
      1
    ],
    "explanation": ""
  },
  {
    "id": 9,
    "date": "20020908",
    "subject": 1,
    "subject_name": "제품디자인론",
    "question_no": 17,
    "question": "구성원리 중 가장 중요한 개념은?",
    "choices": {
      "2": "제품과 인간의 관계를 보다 조화롭게 이끌어 올리도록 노력해야 한다. ❸ 사용하려는 기술과 재료에 대하여 권위자가 되도록 노력 해야 한다.",
      "3": "점진과 리듬",
      "4": "현실의 가능성과 여건을 최대한 활용한다는 자세에서 접 근하고 확대해 나가야 한다.",
      "1": "자신에게 주어진 새 기술과 다른 재료를 이용하여 꾸준 한 제품 디자인에 임해야 한다."
    },
    "answers": [
      1
    ],
    "explanation": ""
  },
  {
    "id": 10,
    "date": "20020908",
    "subject": 2,
    "subject_name": "인간공학",
    "question_no": 29,
    "question": "근시, 원시, 난시 등은 어느 상태를 나타낸 것인가?",
    "choices": {
      "1": "눈의 근접거리 ❷ 안구의 굴절",
      "3": "반복",
      "4": "결정",
      "2": "자극"
    },
    "answers": [
      2
    ],
    "explanation": ""
  },
  {
    "id": 11,
    "date": "20020908",
    "subject": 2,
    "subject_name": "인간공학",
    "question_no": 31,
    "question": "손의 지각 기능 중 형태나 크기를 아는 기능은?",
    "choices": {
      "2": "중량식별 기능",
      "3": "사다리",
      "4": "구름다리",
      "1": "경사로 ❷ 계단"
    },
    "answers": [
      1
    ],
    "explanation": ""
  },
  {
    "id": 12,
    "date": "20020908",
    "subject": 2,
    "subject_name": "인간공학",
    "question_no": 35,
    "question": "색에는 물체색과 광원색이 있다. 다음 중 광원색을 나타내 는 것은?",
    "choices": {
      "2": "의자 등받침 ❸ 지면",
      "3": "색지",
      "4": "다리의 위치",
      "1": "좌석면"
    },
    "answers": [
      1
    ],
    "explanation": ""
  },
  {
    "id": 13,
    "date": "20020908",
    "subject": 3,
    "subject_name": "공업재료 및 모형제작론",
    "question_no": 43,
    "question": "다음 점토모형에 대한 설명 중 틀린 것은?",
    "choices": {
      "1": "인장강도",
      "3": "비교적 신속하게 형태를 구 할 수 있다.",
      "4": "신축율",
      "2": "파열강도 ❸ 인열강도"
    },
    "answers": [
      2
    ],
    "explanation": ""
  },
  {
    "id": 14,
    "date": "20030525",
    "subject": 1,
    "subject_name": "제품디자인론",
    "question_no": 2,
    "question": "다음 중 좁은 의미에서 공업디자인(Industrial Design) 분야 는?",
    "choices": {
      "1": "비례",
      "2": "균형",
      "4": "환경디자인 3. 제품수명주기의 과정 중 동종이질의 상품이 등장하고 기존제 품이 밀려남에 따라 판매가 급격히 하락하고 조업도가 낮아 지는 단계는?",
      "3": "반복 ❹ 균제"
    },
    "answers": [
      3
    ],
    "explanation": ""
  },
  {
    "id": 15,
    "date": "20030525",
    "subject": 1,
    "subject_name": "제품디자인론",
    "question_no": 8,
    "question": "과거의 합리적인 모랄(moral)에 대한 전적인 거절을 위해 1981년 밀라노에서 새로운 그룹의 기반을 조성하였으며, 역 사적 디자인 모티브를 추출하여 재해석하거나 다양한 양식과 혼용, 복합적인 형태를 추구한 운동은? ❶ 멤피스(memphis)",
    "choices": {
      "2": "포스트모더니즘(post-modernism)",
      "3": "키치 스타일",
      "4": "유기적 모더니즘 스타일 10. 20세기 초엽에 인더스트리얼 디자인(Industrial Design)이란 용어를 처음 사용한 사람은?",
      "1": "아르데코 스타일 ❷ 유선형 스타일"
    },
    "answers": [
      1
    ],
    "explanation": ""
  },
  {
    "id": 16,
    "date": "20030525",
    "subject": 2,
    "subject_name": "인간공학",
    "question_no": 35,
    "question": "건물의 내부 색채 도장시 반사율이 가장 적합치 못한 것은?",
    "choices": {
      "1": "허상",
      "2": "활동계",
      "4": "각도계를 장착한 간상계",
      "3": "좌고계"
    },
    "answers": [
      3
    ],
    "explanation": ""
  },
  {
    "id": 17,
    "date": "20030525",
    "subject": 3,
    "subject_name": "공업재료 및 모형제작론",
    "question_no": 49,
    "question": "다음 석고재료 가공과정에 대한 설명 중 틀린 것은?",
    "choices": {
      "1": "양적으로 충분하고 품질이 균일할 것 ❷ 역학적 성질이 완벽할 것",
      "2": "석고 표면 연마는 400-600번의 내수사포를 사용한다.",
      "3": "입수하기가 용이할 것",
      "4": "가공기술적으로 완전할 것"
    },
    "answers": [
      4
    ],
    "explanation": ""
  },
  {
    "id": 18,
    "date": "20030525",
    "subject": 3,
    "subject_name": "공업재료 및 모형제작론",
    "question_no": 53,
    "question": "열가소성 플라스틱 제품의 금형은?",
    "choices": {
      "1": "반압입형",
      "2": "석기",
      "4": "토기",
      "3": "도기"
    },
    "answers": [
      3
    ],
    "explanation": ""
  },
  {
    "id": 19,
    "date": "20030525",
    "subject": 3,
    "subject_name": "공업재료 및 모형제작론",
    "question_no": 55,
    "question": "금속의 일반적 특성에 관한 설명 중 잘못된 것은?",
    "choices": {
      "1": "소금",
      "2": "어교",
      "4": "알부민",
      "3": "카세인"
    },
    "answers": [
      3
    ],
    "explanation": ""
  },
  {
    "id": 20,
    "date": "20030525",
    "subject": 4,
    "subject_name": "색채학",
    "question_no": 64,
    "question": "다음 연색성에 관한 기술 중 틀린 것은?",
    "choices": {
      "1": "색상대비",
      "3": "황색 물체가 녹색광선을 받으면 녹색기미의 황색으로 보 인다.",
      "4": "색조대비",
      "2": "보색대비 ❸ 채도대비"
    },
    "answers": [
      2
    ],
    "explanation": ""
  },
  {
    "id": 21,
    "date": "20030525",
    "subject": 4,
    "subject_name": "색채학",
    "question_no": 67,
    "question": "색을 구별하는 명칭은?",
    "choices": {
      "2": "고유색명 ❸ 계통색명",
      "3": "명암",
      "4": "유행색명",
      "1": "고대색명"
    },
    "answers": [
      1
    ],
    "explanation": ""
  },
  {
    "id": 22,
    "date": "20030525",
    "subject": 4,
    "subject_name": "색채학",
    "question_no": 74,
    "question": "우리나라에서 채택한 산업디자인의 색채 표시방법(K.S)으로 가장 올바른 것은?",
    "choices": {
      "1": "빨강 ❷ 파랑",
      "2": "오스트발트 표색기호와 지정된 일반색명 및 색채견본을 함께 사용하는 것이 이상적이다. ❸ 먼셀 표색기호와 지정된 일반색명 및 색채 견본을 함께 사용하는 것이 이상적이다.",
      "4": "녹색",
      "3": "노랑"
    },
    "answers": [
      3
    ],
    "explanation": ""
  },
  {
    "id": 23,
    "date": "20040523",
    "subject": 1,
    "subject_name": "제품디자인론",
    "question_no": 3,
    "question": "미적 구성원리 중 가장 중요한 것은?",
    "choices": {
      "1": "시리이즈(series) ❷ 유니트(unit)",
      "2": "변화",
      "3": "패밀리(family)",
      "4": "세트(set)"
    },
    "answers": [
      4
    ],
    "explanation": ""
  },
  {
    "id": 24,
    "date": "20040523",
    "subject": 1,
    "subject_name": "제품디자인론",
    "question_no": 5,
    "question": "디자인 운동과 그 운동의 중심적 인물의 관계설정이 잘못된 것은?",
    "choices": {
      "1": "구조(construction)",
      "2": "재료(material) ❸ 환경(environment)",
      "3": "드스틸 : 몬드리안 ❹ 독일공작연맹 : 말레비치 6. 기능주의(functionalism)는 기능을 건축이나 디자인의 핵심 또는 지배적 요소라고 보는 입장을 가르키는 말이다. 이러한 기능주의의 원리와 거리가 먼 것은?",
      "4": "형태와 기능(form &function)"
    },
    "answers": [
      4
    ],
    "explanation": ""
  },
  {
    "id": 25,
    "date": "20040523",
    "subject": 1,
    "subject_name": "제품디자인론",
    "question_no": 7,
    "question": "디자인 매니저가 갖추어야 할 자질에 포함되지 않는 것은?",
    "choices": {
      "1": "오토 바그너(Otto Wagner)",
      "2": "헨리 반 데 벨데(Henri Van de velde) ❸ 윌리엄 모리스(William Morris)",
      "3": "예견력 ❹ 독단력 8. 영국에서 아트 앤드 크라프트(Art and Crafts)운동을 일으킨 사람은?",
      "4": "요셉 호프만(Josef Hoffmann)"
    },
    "answers": [
      4
    ],
    "explanation": ""
  },
  {
    "id": 26,
    "date": "20040523",
    "subject": 1,
    "subject_name": "제품디자인론",
    "question_no": 13,
    "question": "다음 중 3차원 디자인에 해당되는 것은?",
    "choices": {
      "1": "제품의 단순화",
      "2": "부품의 표준화 ❸ 외형의 세련화",
      "3": "핸리 드레이퍼스(Henry Dreyfuss)",
      "4": "공정의 전문화"
    },
    "answers": [
      4
    ],
    "explanation": ""
  },
  {
    "id": 27,
    "date": "20040523",
    "subject": 1,
    "subject_name": "제품디자인론",
    "question_no": 16,
    "question": "아이디어 발상의 폭을 넓히는 방법 중 '유사 연상'에 대한 사례는?",
    "choices": {
      "1": "반복(repitition)",
      "3": "여자에 대하여 립스틱을 떠올린다",
      "4": "비례(proportion)",
      "2": "균형(balance) ❸ 균제(symmetry)"
    },
    "answers": [
      2
    ],
    "explanation": ""
  },
  {
    "id": 28,
    "date": "20040523",
    "subject": 1,
    "subject_name": "제품디자인론",
    "question_no": 19,
    "question": "독일공작연맹(DWB)에 대한 설명 중 잘못된 것은?",
    "choices": {
      "1": "2시",
      "2": "6시 ❸ 9시",
      "3": "전위적 조형운동",
      "4": "12시"
    },
    "answers": [
      4
    ],
    "explanation": ""
  },
  {
    "id": 29,
    "date": "20040523",
    "subject": 2,
    "subject_name": "인간공학",
    "question_no": 28,
    "question": "다음은 인간공학과 관계된 학문 영역 중 가장 관계 먼 것 은?",
    "choices": {
      "1": "인간체계의 과학",
      "2": "2:1",
      "3": "4:1",
      "4": "5:1"
    },
    "answers": [
      4
    ],
    "explanation": ""
  },
  {
    "id": 30,
    "date": "20040523",
    "subject": 2,
    "subject_name": "인간공학",
    "question_no": 32,
    "question": "인간 기계 시스템에서 인간이 하지 않아도 좋은 것은?",
    "choices": {
      "1": "크기, 모양, 색상, 상징성 등이 눈에 잘띄어야 한다.",
      "2": "읽기 편해야 한다. ❸ 간결해야 하므로 가능한 한 준말을 사용한다.",
      "3": "색채조명 ❹ 방향조명 35. 인간공학적 설계원칙 중 경고 표지판 제작시 유의할 사항이 잘못된 것은?",
      "4": "표준 규격에 맞추어야 한다."
    },
    "answers": [
      4
    ],
    "explanation": ""
  },
  {
    "id": 31,
    "date": "20040523",
    "subject": 2,
    "subject_name": "인간공학",
    "question_no": 38,
    "question": "빛의 강도와 시각과의 관계에 있어서 맞는 말은? ❶ 배경이 어두우면 약한 빛이 비교적 확실히 보인다.",
    "choices": {
      "2": "최대 염력 ❸ 최대 근력",
      "3": "배경이 어두우면 약한 빛은 보이지 않는다.",
      "4": "최대 완력",
      "1": "최대 지구력"
    },
    "answers": [
      1
    ],
    "explanation": ""
  },
  {
    "id": 32,
    "date": "20040523",
    "subject": 3,
    "subject_name": "공업재료 및 모형제작론",
    "question_no": 41,
    "question": "다음 중 열가소성 수지가 아닌 것은?",
    "choices": {
      "1": "드로잉(drawing) ❷ 모델링(modeling)",
      "2": "폴리에틸렌 (Polyethylene) 수지",
      "3": "테크니컬 일러스트레이션(technical illustration)",
      "4": "렌더링(rendering)"
    },
    "answers": [
      4
    ],
    "explanation": ""
  },
  {
    "id": 33,
    "date": "20040523",
    "subject": 3,
    "subject_name": "공업재료 및 모형제작론",
    "question_no": 46,
    "question": "플라스틱 재료가 갖는 장점이 아닌 것은?",
    "choices": {
      "1": "오버래핑 (overlapping) ❷ 트래핑 (trapping)",
      "3": "믹싱 (mixing)",
      "4": "템퍼링 (tempering)",
      "2": "소석고 플라스터"
    },
    "answers": [
      2
    ],
    "explanation": ""
  },
  {
    "id": 34,
    "date": "20040523",
    "subject": 3,
    "subject_name": "공업재료 및 모형제작론",
    "question_no": 57,
    "question": "다음의 3면도를 보고 유추할 수 있는 입체는?",
    "choices": {
      "1": "저주파용 전기자기",
      "3": "패리안 자기 ❹ 식기용 자기",
      "4": "t 60. 충격강도를 크게 하고 간단한 제조공정이 가능하도록 발전 시킨 소지로서, 얇은 단면은 투과성이 있으며 cone 9~11(1250℃~1285℃)에서 소성되는 자기는?",
      "2": "결정자기"
    },
    "answers": [
      2
    ],
    "explanation": ""
  },
  {
    "id": 35,
    "date": "20040523",
    "subject": 4,
    "subject_name": "색채학",
    "question_no": 68,
    "question": "색의 맑거나 흐린 정도의 차를 의미하는 것은?",
    "choices": {
      "1": "명도 ❷ 채도",
      "3": "주파장 → 채도, 휘도 → 명도, 순도 → 색상",
      "4": "주파장 → 색상, 휘도 → 채도, 순도 → 명도",
      "2": "주파장 → 명도, 휘도 → 색상, 순도 → 채도"
    },
    "answers": [
      2
    ],
    "explanation": ""
  },
  {
    "id": 36,
    "date": "20040905",
    "subject": 1,
    "subject_name": "제품디자인론",
    "question_no": 1,
    "question": "다음 중 그린 디자인(Green Design)과 관계 없는 것은?",
    "choices": {
      "1": "아트앤드크라프트 ❷ 아르누보",
      "2": "사전 오염방지",
      "3": "독일공작연맹",
      "4": "바우하우스"
    },
    "answers": [
      4
    ],
    "explanation": ""
  },
  {
    "id": 37,
    "date": "20040905",
    "subject": 1,
    "subject_name": "제품디자인론",
    "question_no": 3,
    "question": "미적 형식 원리인 율동(rhythm)에 관한 설명 중 틀린 것은?",
    "choices": {
      "1": "각 부분이 동일하며 간격이 일정할 때는 리듬이 단조롭 다.",
      "2": "정3각형과 정6각형",
      "4": "정4각형과 정6각형",
      "3": "정4각형과 정5각형"
    },
    "answers": [
      3
    ],
    "explanation": ""
  },
  {
    "id": 38,
    "date": "20040905",
    "subject": 1,
    "subject_name": "제품디자인론",
    "question_no": 5,
    "question": "과거의 합리적인 모랄(moral)에 대한 전적인 거절을 위해 1981년 밀라노에서 새로운 그룹의 기반을 조성하였으며, 역 사적 디자인 모티브를 추출하여 재해석하거나 다양한 양식과 혼용, 복합적인 형태를 추구한 운동은? ❶ 멤피스(memphis)",
    "choices": {
      "2": "포스트모더니즘(post-modernism)",
      "3": "모서(K.Mosere)",
      "4": "월리엄 모리스(William Morris)",
      "1": "헨리 반데 벨데(Henry van de velde) ❷ 레이몬드 로위(Raymond Loewy)"
    },
    "answers": [
      1
    ],
    "explanation": ""
  },
  {
    "id": 39,
    "date": "20040905",
    "subject": 1,
    "subject_name": "제품디자인론",
    "question_no": 8,
    "question": "공업디자인에 있어 제품의 완성 예상도를 뜻하는 것은?",
    "choices": {
      "1": "스타일 스켓치(style sketch) ❷ 렌더링(rendering)",
      "3": "외부지향적 소비유형",
      "4": "모방지향적 소비유형",
      "2": "욕구지향적 소비유형"
    },
    "answers": [
      2
    ],
    "explanation": ""
  },
  {
    "id": 40,
    "date": "20040905",
    "subject": 1,
    "subject_name": "제품디자인론",
    "question_no": 11,
    "question": "루이스설리반이 주장한 기능주의 미학의 구호가 맞는 것은?",
    "choices": {
      "1": "존러스킨",
      "3": "대체법",
      "4": "찰스레니맥킨토시",
      "2": "루이스설리반 ❸ 프랭크로이드라이트"
    },
    "answers": [
      2
    ],
    "explanation": ""
  },
  {
    "id": 41,
    "date": "20040905",
    "subject": 2,
    "subject_name": "인간공학",
    "question_no": 22,
    "question": "국지적인 근육의 동작강도를 측정하는 방법은?",
    "choices": {
      "2": "제1차 세계대전 이후 ❸ 제2차 세계대전 이후",
      "3": "소음 계측",
      "4": "월남전 이후",
      "1": "산업혁명 이후"
    },
    "answers": [
      1
    ],
    "explanation": ""
  },
  {
    "id": 42,
    "date": "20040905",
    "subject": 2,
    "subject_name": "인간공학",
    "question_no": 24,
    "question": "제어/반응비(control/response ratio)에 대한 설명 중 잘못된 것은?",
    "choices": {
      "1": "0.01 %",
      "2": "0.2 %",
      "4": "제어/반응비가 감소함에 따라 이동시간은 급격히 감소하 다가 안정되며, 조정시간은 이와 반대의 형태를 갖는다. 25. 사람이 거주하는 방안에서의 탄산가스 농도는 몇 % 이하여 야 하는가?",
      "3": "0.25 % ❹ 0.5 %"
    },
    "answers": [
      3
    ],
    "explanation": ""
  },
  {
    "id": 43,
    "date": "20040905",
    "subject": 2,
    "subject_name": "인간공학",
    "question_no": 27,
    "question": "다음 표준형 키보드의 경사도 중 최적 유지의 각도는?",
    "choices": {
      "1": "좌우 60° ❷ 좌우 120°",
      "2": "7° - 10° ❸ 15° - 25°",
      "4": "좌우 360°",
      "3": "좌우 180°"
    },
    "answers": [
      3
    ],
    "explanation": ""
  },
  {
    "id": 44,
    "date": "20040905",
    "subject": 2,
    "subject_name": "인간공학",
    "question_no": 33,
    "question": "다음 중 자동차나 비행기의 조종간을 설계할 때 가장 적절 하게 응용되는 양립성은?",
    "choices": {
      "1": "남성의 제 5백분위수",
      "3": "남성의 제 50백분위수 ❹ 남성의 제 95백분위수",
      "4": "형식 양립성(modality compatibility) 34. 항공기의 설계시 비상 탈출구의 크기를 정할 때 인체 측정 자료 중 어떤 것을 이용하는 것이 가장 타당한가?",
      "2": "여성의 제 5백분위수"
    },
    "answers": [
      2
    ],
    "explanation": ""
  },
  {
    "id": 45,
    "date": "20040905",
    "subject": 3,
    "subject_name": "공업재료 및 모형제작론",
    "question_no": 46,
    "question": "사출성형의 특징이 아닌 것은? ❶ 살두께 최소 0.05m/m도 성형이 가능하다.",
    "choices": {
      "2": "고속, 대량, 자동화 생산이 가능하다.",
      "3": "항장식",
      "4": "항상식",
      "1": "항원식 ❷ 항중식"
    },
    "answers": [
      1
    ],
    "explanation": ""
  },
  {
    "id": 46,
    "date": "20040905",
    "subject": 3,
    "subject_name": "공업재료 및 모형제작론",
    "question_no": 49,
    "question": "금속모형제작에 필요한 관굽힘 작업 방법 중 맞는 것은? ❶ 가볍고 가는 관에는 스프링을 사용하고, 두꺼운 관에는 쇠구슬을 사용한다.",
    "choices": {
      "2": "플라스틱",
      "3": "게르마늄",
      "4": "마그네슘",
      "1": "바이스 ❷ 크램프"
    },
    "answers": [
      1
    ],
    "explanation": ""
  },
  {
    "id": 47,
    "date": "20040905",
    "subject": 3,
    "subject_name": "공업재료 및 모형제작론",
    "question_no": 59,
    "question": "다음 중 농담효과를 풍부하게 얻을 수 있기 때문에 사진인 쇄에 가장 적합한 것은?",
    "choices": {
      "2": "커머셜 브론즈(Commercial bronze) ❸ 길딩 메탈(Gilding metal)",
      "3": "플록 인쇄",
      "4": "로우 브라스(low brass)",
      "1": "톰백(Tombac)"
    },
    "answers": [
      1
    ],
    "explanation": ""
  },
  {
    "id": 48,
    "date": "20040905",
    "subject": 4,
    "subject_name": "색채학",
    "question_no": 62,
    "question": "기업색채의 계획방법에 관한 설명 중 가장 올바른 것은?",
    "choices": {
      "1": "자극적, 서늘함",
      "2": "안정감, 온도감",
      "4": "동색 계열의 색채로 계획하여야 한다. 63. 문.스펜서 색채조화론의 균형점에서 색상 YR, 채도가 5보다 클 때 심리적 효과는?",
      "3": "안정감, 중성감 ❹ 자극적, 따뜻함"
    },
    "answers": [
      3
    ],
    "explanation": ""
  },
  {
    "id": 49,
    "date": "20040905",
    "subject": 4,
    "subject_name": "색채학",
    "question_no": 67,
    "question": "보색대비의 효과를 주기에 가장 적절한 배색은?",
    "choices": {
      "2": "동일색상면 도표",
      "3": "명도 및 채도 단계 도표 ❹ 색입체",
      "4": "빨강-보라 68. 무채색의 명도단계를 축으로 하여 색상, 명도, 채도를 단계 적으로 배열한 기구는?",
      "1": "색상환 도표"
    },
    "answers": [
      1
    ],
    "explanation": ""
  },
  {
    "id": 50,
    "date": "20040905",
    "subject": 4,
    "subject_name": "색채학",
    "question_no": 73,
    "question": "다음 중 우울, 무기력을 연상시키는 색은?",
    "choices": {
      "1": "명순응",
      "3": "채도대비",
      "4": "무채순응",
      "2": "색순응 ❸ 암순응"
    },
    "answers": [
      2
    ],
    "explanation": ""
  },
  {
    "id": 51,
    "date": "20050529",
    "subject": 1,
    "subject_name": "제품디자인론",
    "question_no": 1,
    "question": "국민생활 수준을 향상시키고 환경을 보존하는 것은 산업디자 인의 어느 기능에 속하는가?",
    "choices": {
      "1": "도무스 아카데미(Domus) 아카데미 ❷ 울름(Ulm) 디자인 대학",
      "2": "생리적 기능",
      "3": "왕립 미술학교",
      "4": "IIT(Illinois Institute Technology)"
    },
    "answers": [
      4
    ],
    "explanation": ""
  },
  {
    "id": 52,
    "date": "20050529",
    "subject": 1,
    "subject_name": "제품디자인론",
    "question_no": 7,
    "question": "신제품 개발을 위한 아이디어 원천으로 적합하지 않은 것은?",
    "choices": {
      "1": "소비자 및 판매점의 의견",
      "2": "레이몬드 로위",
      "4": "모홀리 나기",
      "3": "티이크"
    },
    "answers": [
      3
    ],
    "explanation": ""
  },
  {
    "id": 53,
    "date": "20050529",
    "subject": 1,
    "subject_name": "제품디자인론",
    "question_no": 14,
    "question": "Market Share의 가장 올바른 설명은?",
    "choices": {
      "1": "아이디어 선정 단계",
      "3": "윌리엄 모리스",
      "4": "상품화 단계",
      "2": "시장 시험 단계 ❸ 사업성 분석 단계"
    },
    "answers": [
      2
    ],
    "explanation": ""
  },
  {
    "id": 54,
    "date": "20050529",
    "subject": 1,
    "subject_name": "제품디자인론",
    "question_no": 17,
    "question": "디자인의 원리로서 적합치 않은 것은?",
    "choices": {
      "1": "대비 ❷ 장식",
      "3": "경제성",
      "4": "기능성",
      "2": "재료성"
    },
    "answers": [
      2
    ],
    "explanation": ""
  },
  {
    "id": 55,
    "date": "20050529",
    "subject": 3,
    "subject_name": "공업재료 및 모형제작론",
    "question_no": 54,
    "question": "다음 중 프로토 타입(proto type)모델과 같은 내용의 것은?",
    "choices": {
      "2": "더미 모델",
      "3": "조립도",
      "4": "상세도",
      "1": "승인도 ❷ 제작도"
    },
    "answers": [
      1
    ],
    "explanation": ""
  },
  {
    "id": 56,
    "date": "20050529",
    "subject": 3,
    "subject_name": "공업재료 및 모형제작론",
    "question_no": 58,
    "question": "도면에 치수기입시 제일 집중적으로 기입하는 투상도는?",
    "choices": {
      "1": "스케치 모형(Sketch Model)",
      "3": "좌측면도",
      "4": "러프 모형(Rough Model)",
      "2": "워킹 모형(Working Model) ❸ 스케일 모형(Scale Model)"
    },
    "answers": [
      2
    ],
    "explanation": ""
  },
  {
    "id": 57,
    "date": "20050529",
    "subject": 3,
    "subject_name": "공업재료 및 모형제작론",
    "question_no": 60,
    "question": "사출성형에 관한 설명 중 잘못된 것은?",
    "choices": {
      "1": "눈의 긴장과 피로가 감소된다.",
      "2": "보다 빨리 판단할 수 있다. ❸ 색채에 대한 지식이 높아진다.",
      "3": "치수의 정밀도가 높고, 품질이 안정된 성형품을 얻을 수 있다. ❹ 소량제품 생산에 가장 적합하다. 61. 색채 조절을 실시할 때 나타나는 효과와 비교적 관계가 먼 내용은?",
      "4": "사고나 재해를 감소시킨다."
    },
    "answers": [
      4
    ],
    "explanation": ""
  },
  {
    "id": 58,
    "date": "20050529",
    "subject": 4,
    "subject_name": "색채학",
    "question_no": 65,
    "question": "다음은 무채색(無彩色 achromatic color)을 설명한 것들이 다. 옳은 것은?",
    "choices": {
      "1": "녹색",
      "2": "황색 ❸ 청색",
      "3": "색상, 명도는 없고 채도만 있다. ❹ 색상, 채도는 없고 명도만 있다. 66. 흰 종이를 한동안 보다가 회색 종이를 볼 때, 회색 종이의 느낌은?",
      "4": "적색"
    },
    "answers": [
      4
    ],
    "explanation": ""
  },
  {
    "id": 59,
    "date": "20050529",
    "subject": 4,
    "subject_name": "색채학",
    "question_no": 71,
    "question": "다음 오스트발트 표색계에 관한 설명 중 잘못된 것은?",
    "choices": {
      "1": "마티스(Matisse)",
      "3": "헤링(Hering) ❹ 쉐브럴(Chevereul. M. E)",
      "4": "광원색 73. 색채 조화를 유사한 조화와 대비의 조화로 나누고 정량적 색채 조화론을 제시한 사람은?",
      "2": "먼셀(Munsell)"
    },
    "answers": [
      2
    ],
    "explanation": ""
  },
  {
    "id": 60,
    "date": "20050529",
    "subject": 4,
    "subject_name": "색채학",
    "question_no": 76,
    "question": "색상환을 만들 때 고려해야 할 사항은?",
    "choices": {
      "1": "색상대비",
      "3": "연변대비 ❹ 계시대비",
      "4": "색상환상에서 보색관계는 고려할 필요가 없다. 77. TV 화면에 파란바다 풍경을 20초 정도 보여주다가 오렌지 색 상품을 클로즈업시켜 강렬한 인상을 남기려는 시도는 어 떤 대비현상을 이용한 것인가?",
      "2": "채도대비"
    },
    "answers": [
      2
    ],
    "explanation": ""
  },
  {
    "id": 61,
    "date": "20050529",
    "subject": 4,
    "subject_name": "색채학",
    "question_no": 78,
    "question": "다음 중 망막을 이루는 두가지 시세포는?",
    "choices": {
      "2": "40.6 ❸ 29.4",
      "3": "면적대비",
      "4": "16.4",
      "1": "50.4"
    },
    "answers": [
      1
    ],
    "explanation": ""
  },
  {
    "id": 62,
    "date": "20100509",
    "subject": 1,
    "subject_name": "제품디자인론",
    "question_no": 4,
    "question": "팝(pop) 디자인 운동과 관련이 없는 것은?",
    "choices": {
      "1": "Norman Bel Geddes ❷ Louis Sullivan",
      "3": "K.Mosere",
      "4": "Henry Van de Velde",
      "2": "부품의 표준화 ❸ 외형의 세련화"
    },
    "answers": [
      2
    ],
    "explanation": ""
  },
  {
    "id": 63,
    "date": "20100509",
    "subject": 1,
    "subject_name": "제품디자인론",
    "question_no": 8,
    "question": "아이디어 발상 및 전개 단계에서 다음 중 필요성이 가장 적 은 것은?",
    "choices": {
      "2": "스크래치 스케치",
      "3": "1980년",
      "4": "1987년",
      "1": "1960년 ❷ 1970년"
    },
    "answers": [
      1
    ],
    "explanation": ""
  },
  {
    "id": 64,
    "date": "20100509",
    "subject": 1,
    "subject_name": "제품디자인론",
    "question_no": 13,
    "question": "크기가 없는 점과 폭이 없는 선의 형태적 분류는?",
    "choices": {
      "1": "자연적 형태 ❷ 이념적 형태",
      "3": "ColD",
      "4": "ICSID",
      "2": "Bauhaus"
    },
    "answers": [
      2
    ],
    "explanation": ""
  },
  {
    "id": 65,
    "date": "20100509",
    "subject": 2,
    "subject_name": "인간공학",
    "question_no": 25,
    "question": "다음 중 눈에 대한 설명으로 틀린 것은?",
    "choices": {
      "1": "0.5 bit",
      "2": "1 bit ❸ 2 bit",
      "3": "원추(cone)세포는 주로 망막의 중심부에 있다. ❹ 수정체는 가까운 곳을 볼 때보다 먼 곳을 볼 때 두꺼워 진다. 26. 계기판에 등이 4개가 있고, 그 중 하나에만 불이 켜지는 경 우와 같이 4개의 대안이 존재한 경우 정보량은 얼마인가?",
      "4": "4 bit"
    },
    "answers": [
      4
    ],
    "explanation": ""
  },
  {
    "id": 66,
    "date": "20100509",
    "subject": 2,
    "subject_name": "인간공학",
    "question_no": 31,
    "question": "다음 중 수치를 정확히 읽어야 할 경우에 가장 적합한 표시 장치의 형태는?",
    "choices": {
      "1": "동침형 표시장치",
      "2": "",
      "4": "",
      "3": ""
    },
    "answers": [
      3
    ],
    "explanation": ""
  },
  {
    "id": 67,
    "date": "20100509",
    "subject": 3,
    "subject_name": "공업재료 및 모형제작론",
    "question_no": 42,
    "question": "일반적인 금속의 성질에 대한 설명 중 틀린 것은?",
    "choices": {
      "1": "15% 이하 ❷ 30% 전후",
      "2": "열, 전기의 양도체이다.",
      "3": "40% 전후",
      "4": "50% 이상"
    },
    "answers": [
      4
    ],
    "explanation": ""
  },
  {
    "id": 68,
    "date": "20100509",
    "subject": 3,
    "subject_name": "공업재료 및 모형제작론",
    "question_no": 50,
    "question": "가축제품에 대한 내용이 옳게 설명된 것은? ❶ 우피 – 은면층이 평활, 미려하고 성질이 견고하여 사용 량이 많다.",
    "choices": {
      "2": "마피 – 마찰에 강하고 평호라하며 감촉이 좋다.",
      "3": "연성",
      "4": "인성",
      "1": "탄성 ❷ 소성"
    },
    "answers": [
      1
    ],
    "explanation": ""
  },
  {
    "id": 69,
    "date": "20100509",
    "subject": 3,
    "subject_name": "공업재료 및 모형제작론",
    "question_no": 56,
    "question": "금속 성형을 위한 가공방법 중에서 모재(母材)의 표면을 파 내고 이 자리에 다른 소재를 채워 넣는 방법으로 금속이나 도자기에 많이 사용하는 방법은?",
    "choices": {
      "1": "블리드(bleed) ❷ 트래핑(trapping)",
      "2": "포밍(Forming)",
      "3": "믹싱(mixing)",
      "4": "템퍼링(tempering)"
    },
    "answers": [
      4
    ],
    "explanation": ""
  },
  {
    "id": 70,
    "date": "20100509",
    "subject": 3,
    "subject_name": "공업재료 및 모형제작론",
    "question_no": 59,
    "question": "종이모형(paper model)제작의 단점은?",
    "choices": {
      "1": "색채변별능력",
      "2": "색채조색능력",
      "4": "석고모형 61. 색채계획에 있어 효고적인 색 지정을 하기 위하여 디자이너 가 갖추어야 할 능력으로 거리가 먼 것은?",
      "3": "색채구성능력 ❹ 심리조사능력"
    },
    "answers": [
      3
    ],
    "explanation": ""
  },
  {
    "id": 71,
    "date": "20100509",
    "subject": 4,
    "subject_name": "색채학",
    "question_no": 79,
    "question": "다음 중 채도가 가장 높은 색상은?",
    "choices": {
      "2": "조건등색 ❸ 연색성",
      "3": "보라",
      "4": "표준광",
      "1": "작열현상"
    },
    "answers": [
      1
    ],
    "explanation": ""
  }
]